kittycad/__init__.py
kittycad/_binary.py
kittycad/_downloads.py
kittycad/_file_inputs.py
kittycad/_io_types.py
kittycad/_multipart.py
kittycad/_progress.py
kittycad/client.py
kittycad/exceptions.py
kittycad/pagination.py
kittycad/py.typed
kittycad/response_helpers.py
kittycad/types.py
kittycad/models/__init__.py
kittycad/models/account_provider.py
kittycad/models/add_hole_from_offset.py
kittycad/models/add_org_member.py
kittycad/models/address.py
kittycad/models/address_details.py
kittycad/models/adjacency_info.py
kittycad/models/angle.py
kittycad/models/annotation_basic_dimension.py
kittycad/models/annotation_feature_control.py
kittycad/models/annotation_feature_tag.py
kittycad/models/annotation_line_end.py
kittycad/models/annotation_line_end_options.py
kittycad/models/annotation_mbd_basic_dimension.py
kittycad/models/annotation_mbd_control_frame.py
kittycad/models/annotation_options.py
kittycad/models/annotation_text_alignment_x.py
kittycad/models/annotation_text_alignment_y.py
kittycad/models/annotation_text_options.py
kittycad/models/annotation_type.py
kittycad/models/api_call_query_group.py
kittycad/models/api_call_query_group_by.py
kittycad/models/api_call_status.py
kittycad/models/api_call_with_price.py
kittycad/models/api_call_with_price_results_page.py
kittycad/models/api_endpoint.py
kittycad/models/api_error.py
kittycad/models/api_token.py
kittycad/models/api_token_results_page.py
kittycad/models/api_token_uuid.py
kittycad/models/app_client_info.py
kittycad/models/async_api_call.py
kittycad/models/async_api_call_output.py
kittycad/models/async_api_call_results_page.py
kittycad/models/async_api_call_type.py
kittycad/models/auth_api_key_response.py
kittycad/models/auth_callback.py
kittycad/models/axis.py
kittycad/models/axis_direction_pair.py
kittycad/models/base.py
kittycad/models/base64data.py
kittycad/models/batch_response.py
kittycad/models/billing_info.py
kittycad/models/block_reason.py
kittycad/models/body_type.py
kittycad-1.3.0.dist-info/licenses/LICENSE
kittycad-1.3.0.dist-info/METADATA
kittycad-1.3.0.dist-info/WHEEL
kittycad-1.3.0.dist-info/top_level.txt
kittycad-1.3.0.dist-info/RECORD
